LICENSE.txt
MANIFEST.in
README.md
about.md
requirements.txt
setup.py
Orange3_WONDER_1.egg-info/PKG-INFO
Orange3_WONDER_1.egg-info/SOURCES.txt
Orange3_WONDER_1.egg-info/dependency_links.txt
Orange3_WONDER_1.egg-info/entry_points.txt
Orange3_WONDER_1.egg-info/namespace_packages.txt
Orange3_WONDER_1.egg-info/requires.txt
Orange3_WONDER_1.egg-info/top_level.txt
orangecontrib/__init__.py
orangecontrib/wonder/__init__.py
orangecontrib/wonder/controller/__init__.py
orangecontrib/wonder/controller/fit/__init__.py
orangecontrib/wonder/controller/fit/fit_global_parameters.py
orangecontrib/wonder/controller/fit/fit_parameter.py
orangecontrib/wonder/controller/fit/fitter.py
orangecontrib/wonder/controller/fit/fitter_factory.py
orangecontrib/wonder/controller/fit/wppm_functions.py
orangecontrib/wonder/controller/fit/wppm_functions_multipool.py
orangecontrib/wonder/controller/fit/__test/__init__.py
orangecontrib/wonder/controller/fit/__test/test.py
orangecontrib/wonder/controller/fit/__test/wulff.py
orangecontrib/wonder/controller/fit/data/__init__.py
orangecontrib/wonder/controller/fit/data/atomic_scattering_factor_coefficients.dat
orangecontrib/wonder/controller/fit/data/delta_l_files/100.FTinfo
orangecontrib/wonder/controller/fit/data/delta_l_files/110.FTinfo
orangecontrib/wonder/controller/fit/data/delta_l_files/111.FTinfo
orangecontrib/wonder/controller/fit/data/delta_l_files/200.FTinfo
orangecontrib/wonder/controller/fit/data/delta_l_files/220.FTinfo
orangecontrib/wonder/controller/fit/data/delta_l_files/222.FTinfo
orangecontrib/wonder/controller/fit/data/delta_l_files/311.FTinfo
orangecontrib/wonder/controller/fit/data/delta_l_files/331.FTinfo
orangecontrib/wonder/controller/fit/data/delta_l_files/333.FTinfo
orangecontrib/wonder/controller/fit/data/delta_l_files/400.FTinfo
orangecontrib/wonder/controller/fit/data/delta_l_files/420.FTinfo
orangecontrib/wonder/controller/fit/data/delta_l_files/422.FTinfo
orangecontrib/wonder/controller/fit/data/delta_l_files/440.FTinfo
orangecontrib/wonder/controller/fit/data/delta_l_files/442.FTinfo
orangecontrib/wonder/controller/fit/data/delta_l_files/444.FTinfo
orangecontrib/wonder/controller/fit/data/delta_l_files/511.FTinfo
orangecontrib/wonder/controller/fit/data/delta_l_files/531.FTinfo
