Metadata-Version: 1.1
Name: Orange3-WONDER-1
Version: 1.0.32
Summary: Whole POwder PatterN MoDEl in Orange.
Home-page: https://github.com/WONDER-project/Orange3-WONDER
Author: Luca Rebuffi, Paolo Scardi, Alberto Flor
Author-email: paolo.scardi@unitn.ut
License: GPL3+
Keywords: orange3 add-on,orange3-wonder-1
Platform: UNKNOWN
Classifier: Development Status :: 1 - Planning
Classifier: Intended Audience :: Education
Classifier: Intended Audience :: Science/Research
Classifier: License :: OSI Approved :: GNU General Public License v3 or later (GPLv3+)
Classifier: Programming Language :: Python :: 3 :: Only
